README.md
setup.py
./attention/A2Atttention.py
./attention/ACmixAttention.py
./attention/AFT.py
./attention/Axial_attention.py
./attention/BAM.py
./attention/CBAM.py
./attention/CoAtNet.py
./attention/CoTAttention.py
./attention/CoordAttention.py
./attention/CrissCrossAttention.py
./attention/Crossformer.py
./attention/DANet.py
./attention/DAT.py
./attention/ECAAttention.py
./attention/EMSA.py
./attention/ExternalAttention.py
./attention/HaloAttention.py
./attention/MOATransformer.py
./attention/MUSEAttention.py
./attention/MobileViTAttention.py
./attention/MobileViTv2Attention.py
./attention/OutlookAttention.py
./attention/PSA.py
./attention/ParNetAttention.py
./attention/PolarizedSelfAttention.py
./attention/ResidualAttention.py
./attention/S2Attention.py
./attention/SEAttention.py
./attention/SGE.py
./attention/SKAttention.py
./attention/SelfAttention.py
./attention/ShuffleAttention.py
./attention/SimAM.py
./attention/SimplifiedSelfAttention.py
./attention/TripletAttention.py
./attention/UFOAttention.py
./attention/ViP.py
./attention/__init__.py
./attention/gfnet.py
./backbone/CMT.py
./backbone/CPVT.py
./backbone/CaiT.py
./backbone/CeiT.py
./backbone/CoaT.py
./backbone/ConTNet.py
./backbone/ConViT.py
./backbone/Container.py
./backbone/ConvMixer.py
./backbone/CrossViT.py
./backbone/DViT.py
./backbone/DeiT.py
./backbone/EfficientFormer.py
./backbone/HATNet.py
./backbone/LeViT.py
./backbone/MobileViT.py
./backbone/PIT.py
./backbone/PVT.py
./backbone/PatchConvnet.py
./backbone/ShuffleTransformer.py
./backbone/TnT.py
./backbone/VOLO.py
./backbone/__init__.py
./backbone/resnet.py
./backbone/resnext.py
./conv/CondConv.py
./conv/DepthwiseSeparableConvolution.py
./conv/DynamicConv.py
./conv/HorNet.py
./conv/Involution.py
./conv/MBConv.py
./conv/__init__.py
./mlp/__init__.py
./mlp/g_mlp.py
./mlp/mlp_mixer.py
./mlp/repmlp.py
./mlp/resmlp.py
./mlp/sMLP_block.py
./mlp/vip-mlp.py
./rep/__init__.py
./rep/acnet.py
./rep/ddb.py
./rep/mobileone.py
./rep/repvgg.py
fightingcv.egg-info/PKG-INFO
fightingcv.egg-info/SOURCES.txt
fightingcv.egg-info/dependency_links.txt
fightingcv.egg-info/top_level.txt