Metadata-Version: 2.1
Name: fightingcv
Version: 1.0.1
Summary: FightingCV Codebase For Attention,Backbone, MLP, Re-parameter, Convolution
Home-page: https://github.com/xmu-xiaoma666/External-Attention-pytorch
Author: xmu-xiaoma666
Author-email: julien@huggingface.co
License: Apache
Keywords: AttentionBackbone
Platform: UNKNOWN
Classifier: Intended Audience :: Developers
Classifier: Intended Audience :: Education
Classifier: Intended Audience :: Science/Research
Classifier: License :: OSI Approved :: Apache Software License
Classifier: Operating System :: OS Independent
Classifier: Programming Language :: Python :: 3
Classifier: Topic :: Scientific/Engineering :: Artificial Intelligence
Requires-Python: >=3.7.0
